freqtrade_client/__init__.py
freqtrade_client/ft_client.py
freqtrade_client/ft_rest_client.py
freqtrade_client-2025.12.dist-info/licenses/LICENSE
freqtrade_client-2025.12.dist-info/METADATA
freqtrade_client-2025.12.dist-info/WHEEL
freqtrade_client-2025.12.dist-info/entry_points.txt
freqtrade_client-2025.12.dist-info/top_level.txt
freqtrade_client-2025.12.dist-info/RECORD
