Metadata-Version: 2.4
Name: freqtrade-client
Version: 2025.12
Summary: Freqtrade - Client scripts
Author: Freqtrade Team
Author-email: Freqtrade Team <freqtrade@protonmail.com>
License: GPLv3
Project-URL: Homepage, https://github.com/freqtrade/freqtrade
Project-URL: Documentation, https://freqtrade.io
Project-URL: Bug Tracker, https://github.com/freqtrade/freqtrade/issues
Classifier: Environment :: Console
Classifier: Intended Audience :: Science/Research
Classifier: License :: OSI Approved :: GNU General Public License v3 (GPLv3)
Classifier: Programming Language :: Python :: 3.11
Classifier: Programming Language :: Python :: 3.12
Classifier: Programming Language :: Python :: 3.13
Classifier: Operating System :: MacOS
Classifier: Operating System :: Unix
Classifier: Topic :: Office/Business :: Financial :: Investment
Requires-Python: >=3.11
License-File: LICENSE
Requires-Dist: requests>=2.26.0
Requires-Dist: python-rapidjson>=1.0
Dynamic: license-file
